{
  "debug_id": "d1e08ac7-0a66-46e6-a62e-9df0e60024ac",
  "timestamp_inicio": "2026-06-10T17:55:38.443903Z",
  "ambiente": {
    "debug": true,
    "database_alias": "saveweb001"
  },
  "tabelas_tributacao": {
    "versao": "Padrão"
  },
  "nota": {
    "id": 151,
    "modelo": "55",
    "serie": "001",
    "numero": "44",
    "empresa": "1",
    "filial": "1",
    "destinatario_id": "5",
    "uf_origem": "PR",
    "uf_destino": "PR",
    "regime": "1"
  },
  "itens": [
    {
      "id": 234,
      "produto_id": "ARQLVT1.6",
      "descricao_produto": "PISO VINILICO MAGNIFIQUE LOUISE 184X1220MM",
      "ncm_produto": "3918****",
      "cfop_inicial": "5102",
      "quantidade": "101.0000",
      "unitario": "73.9300",
      "desconto": "0.0000",
      "logs": [
        {
          "id": "22f4f37f-9c6e-4096-8571-2f694fa09d32",
          "timestamp": "2026-06-10T17:55:38.581698Z",
          "tipo": "antes_calculo_item",
          "mensagem": "Início do cálculo de impostos para o item.",
          "dados": {
            "uf_origem": "PR",
            "uf_destino": "PR",
            "regime": "1",
            "tipo_operacao": "VENDA"
          }
        }
      ],
      "fonte_tributacao": "SPARTACUS",
      "cfop_resolvido": "5102",
      "cfop_flags": {
        "exig_icms": false,
        "exig_ipi": false,
        "exig_pis_cofins": false,
        "exig_cbs": false,
        "exig_ibs": false,
        "gera_st": false
      },
      "ncm_resolvido": "3918****",
      "bases": {
        "raiz": "7466.93",
        "icms": "0.00",
        "st": null
      },
      "aliquotas": {
        "ipi": null,
        "icms": "0.00",
        "st": null,
        "pis": "0.00",
        "cofins": "0.00",
        "cbs": null,
        "ibs": null
      },
      "valores_calculados": {
        "ipi": null,
        "icms": "0.00",
        "st": null,
        "pis": "0",
        "cofins": "0",
        "cbs": null,
        "ibs": null
      },
      "extras": {
        "mva_st": null,
        "beneficio_fiscal": null,
        "ibscbs_cst": null,
        "ibscbs_cclasstrib": null
      },
      "csts": {
        "ipi": null,
        "icms": "102",
        "st": null,
        "pis": "49",
        "cofins": "49",
        "cbs": null,
        "ibs": null
      },
      "condicionais_aplicadas": {
        "icms_habilitado_cfop": false,
        "ipi_habilitado_cfop": false,
        "pis_cofins_habilitado_cfop": false,
        "cbs_habilitado_cfop": false,
        "ibs_habilitado_cfop": false
      }
    },
    {
      "id": 233,
      "produto_id": "2",
      "descricao_produto": "PORCELANATO",
      "ncm_produto": "4016****",
      "cfop_inicial": "5102",
      "quantidade": "501.0000",
      "unitario": "207.0000",
      "desconto": "0.0000",
      "logs": [
        {
          "id": "6966c0ae-09fd-4088-b31b-28ecb537ee1c",
          "timestamp": "2026-06-10T17:55:38.924840Z",
          "tipo": "antes_calculo_item",
          "mensagem": "Início do cálculo de impostos para o item.",
          "dados": {
            "uf_origem": "PR",
            "uf_destino": "PR",
            "regime": "1",
            "tipo_operacao": "VENDA"
          }
        }
      ],
      "fonte_tributacao": "SPARTACUS",
      "cfop_resolvido": "5102",
      "cfop_flags": {
        "exig_icms": false,
        "exig_ipi": false,
        "exig_pis_cofins": false,
        "exig_cbs": false,
        "exig_ibs": false,
        "gera_st": false
      },
      "ncm_resolvido": "4016****",
      "bases": {
        "raiz": "103707.00",
        "icms": "0.00",
        "st": null
      },
      "aliquotas": {
        "ipi": null,
        "icms": "0.00",
        "st": null,
        "pis": "0.00",
        "cofins": "0.00",
        "cbs": "0.20",
        "ibs": "0.70"
      },
      "valores_calculados": {
        "ipi": null,
        "icms": "0.00",
        "st": null,
        "pis": "0",
        "cofins": "0",
        "cbs": "207.41",
        "ibs": "725.95"
      },
      "extras": {
        "mva_st": null,
        "beneficio_fiscal": null,
        "ibscbs_cst": "000",
        "ibscbs_cclasstrib": null
      },
      "csts": {
        "ipi": null,
        "icms": "102",
        "st": null,
        "pis": "49",
        "cofins": "49",
        "cbs": "000",
        "ibs": "000"
      },
      "condicionais_aplicadas": {
        "icms_habilitado_cfop": false,
        "ipi_habilitado_cfop": false,
        "pis_cofins_habilitado_cfop": false,
        "cbs_habilitado_cfop": false,
        "ibs_habilitado_cfop": false
      }
    }
  ],
  "logs": [
    {
      "id": "7c01219e-464e-4afd-b288-10653a3df7d5",
      "timestamp": "2026-06-10T17:55:38.558552Z",
      "tipo": "contexto_nota",
      "mensagem": "Contexto fiscal inicial da nota.",
      "dados": {
        "tipo_operacao": "VENDA"
      }
    }
  ],
  "timestamp_fim": "2026-06-10T17:55:39.270894Z"
}